k8s_diagrams/__init__.py
k8s_diagrams-0.0.0.dist-info/LICENSE
k8s_diagrams-0.0.0.dist-info/METADATA
k8s_diagrams-0.0.0.dist-info/WHEEL
k8s_diagrams-0.0.0.dist-info/top_level.txt
k8s_diagrams-0.0.0.dist-info/RECORD
